Workbook

Sheet Sheet1
A1: ID | B1: Hora de início | C1: Hora de conclusão | D1: Email | E1: Nome | F1: Hora da última modificação | G1: Para qual obra deseja regularizar um contrato? | H1: Qual o número da Solicitação? | I1: A solicitação está aprovada? | J1: Qual a descrição Geral do Serviço? | K1: Essa regularização faz parte da carteira de qual setor? | L1: Qual regularização deseja realizar? | M1: Qual o número do contrato no Sienge? | N1: Deseja pontuar mais alguma observação da regularização em questão? | O1: Qual o número do credor? | P1: Qual a descrição do Credor? | Q1: Qual a data de inicio do contrato? | R1: Qual a data de término do contrato? | S1: Adicione uma nota fiscal modelo do fornecedor | T1: Qual o tipo de contrato? | U1: Haverá caução ou retenção nesse contrato? | V1: Deseja pontuar mais alguma observação da elaboração em questão? | W1: Especifique o motivo da compra ter sido feita diretamente pela obra | X1: Especifique a Categoria: | Y1: Adicione uma nota fiscal dos materiais comprados ou proposta final negociada | Z1: Adicione um comprovante de autorização do coordenador da obra: | AA1: Qual o número do credor cadastrado? | AB1: Qual o CNPJ do Credor Cadastrado? | AC1: Qual a descrição código do insumo, quantidade e preço unitário. | AD1: Condição de pagamento negociada | AE1: Deseja pontuar mais alguma observação do pedido em questão?
A2: 29 | B2: 45749.383 | C2: 45749.384 | D2: anonymous | G2: Royal Palace | H2: 72280 | I2: Sim | J2: lavagem fachada | L2: Aditivo de Contrato | M2: CS/960079
A3: 30 | B3: 45749.421 | C3: 45749.456 | D3: anonymous | G3: Royal Plaza | H3: 71774 | I3: Sim | J3: Impermeabilização apto: R$ 13,60/m2 CONTRAPISO: R$ 25,00/m2 | L3: Aditivo de Contrato | M3: CS/2420134
A4: 36 | B4: 45755.476 | C4: 45755.48 | D4: rafael.souza@lbx.com.br | E4: Rafael Barbosa Ramalho de Souza | G4: Royal Legacy | H4: 72790 | I4: Sim | J4: Medição de energia COPEL | L4: Elaboração de Contrato novo | O4: 191 | P4: COPEL | Q4: 45757 | R4: 45848 | S4: https://lbxconstrucao-my.sharepoint.com/personal/lucas_silva_lbx_com_br/Documents/Aplicativos/Microsoft%20Forms/Regulariza%C3%A7%C3%A3o%20de%20contratos%20Sienge%201/Pergunta/LUZ%20(1)_Rafael%20Barbosa%20Ramal.jpeg | T4: Normal
A5: 37 | B5: 45755.573 | C5: 45755.589 | D5: guilherme.aoyama@lbx.com.br | E5: Guilherme Aoyama | G5: Forte de Arundel | H5: 72291 | I5: Sim | J5: Limpeza de canteiro de obras | L5: Elaboração de Contrato novo | O5: 15971 | P5: FLAVIA CARNEIRO DE CARVALHO NEPONUCENA | Q5: 45747 | R5: 45930 | S5: https://lbxconstrucao-my.sharepoint.com/personal/lucas_silva_lbx_com_br/Documents/Aplicativos/Microsoft%20Forms/Regulariza%C3%A7%C3%A3o%20de%20contratos%20Sienge%201/Pergunta/669-cellis%20park%20900189330678_Guilherme%20Aoyama.pdf | T5: Spot
A6: 38 | B6: 45755.589 | C6: 45755.603 | D6: guilherme.aoyama@lbx.com.br | E6: Guilherme Aoyama | G6: Forte de Arundel | H6: 72411 | I6: Sim | J6: Serviço de impermeabilização, rejunte, limpeza grossa, limpeza fina | L6: Elaboração de Contrato novo | O6: 14266 | P6: LF ACABAMENTOS LTDA | Q6: 45809 | R6: 46082 | S6: https://lbxconstrucao-my.sharepoint.com/personal/lucas_silva_lbx_com_br/Documents/Aplicativos/Microsoft%20Forms/Regulariza%C3%A7%C3%A3o%20de%20contratos%20Sienge%201/Pergunta/LBX_Guilherme%20Aoyama.pdf | T6: Normal
A7: 39 | B7: 45755.603 | C7: 45755.605 | D7: guilherme.aoyama@lbx.com.br | E7: Guilherme Aoyama | G7: Forte de Arundel | H7: 71017 | I7: Sim | J7: Execução de chapisco para gesso e gesso corrido | L7: Elaboração de Contrato novo | O7: 16209 | P7: G. M. SOLUÇÕES TERMOACUSTICAS LTDA | Q7: 45792 | R7: 46157 | S7: https://lbxconstrucao-my.sharepoint.com/personal/lucas_silva_lbx_com_br/Documents/Aplicativos/Microsoft%20Forms/Regulariza%C3%A7%C3%A3o%20de%20contratos%20Sienge%201/Pergunta/ENTREVIAS%20%20NF%2046..._Guilherme%20Aoyama.pdf | T7: Normal
A8: 40 | B8: 45761.409 | C8: 45761.41 | D8: eduardo.silva@lbx.com.br | E8: Eduardo Marques da Silva | G8: Royal Legacy | H8: 73155 | I8: Não | J8: Pintura | L8: Aditivo de Contrato | M8: ct/1470022
A9: 41 | B9: 45761.582 | C9: 45761.589 | D9: rafael.souza@lbx.com.br | E9: Rafael Barbosa Ramalho de Souza | G9: Royal Legacy | H9: 70906 | I9: Sim | J9: SERVIÇOS GERAIS DE CONSTRUÇÃO CIVIL | L9: Elaboração de Contrato novo | O9: 16293 | P9: EPOCA PRESTADORA DE SERVICOS LTDA | Q9: 45740 | R9: 45808 | S9: https://lbxconstrucao-my.sharepoint.com/personal/lucas_silva_lbx_com_br/Documents/Aplicativos/Microsoft%20Forms/Regulariza%C3%A7%C3%A3o%20de%20contratos%20Sienge%201/Pergunta/teste_Rafael%20Barbosa%20Ramal.pdf | T9: Normal
A10: 42 | B10: 45761.589 | C10: 45761.592 | D10: rafael.souza@lbx.com.br | E10: Rafael Barbosa Ramalho de Souza | G10: Royal Legacy | H10: 73100 | I10: Sim | J10: FORNECIMENTO DE MARMITA | L10: Elaboração de Contrato novo | O10: 15036 | P10: LUIZ CARLOS VASQUEZ (VIVIAN) | Q10: 45761 | R10: 45838 | S10: https://lbxconstrucao-my.sharepoint.com/personal/lucas_silva_lbx_com_br/Documents/Aplicativos/Microsoft%20Forms/Regulariza%C3%A7%C3%A3o%20de%20contratos%20Sienge%201/Pergunta/410830422549530810001730000000000032250322611_Rafael%20Barbosa%20Ramal.pdf | T10: Normal
A11: 43 | B11: 45763.583 | C11: 45763.584 | D11: rafael.souza@lbx.com.br | E11: Rafael Barbosa Ramalho de Souza | G11: Royal Legacy | H11: 73368 | I11: Não | J11: LAMINADO E PORTAS DE MADEIRA | L11: Aditivo de Contrato | M11: CS/1470088 | N11: NÃO
A12: 44 | B12: 45763.621 | C12: 45763.622 | D12: rafael.souza@lbx.com.br | E12: Rafael Barbosa Ramalho de Souza | G12: Royal Legacy | H12: 73377 | I12: Não | J12: INSTALAÇÃO DE ESQUADRIAS | L12: Aditivo de Contrato | M12: CS/1470127 | N12: NÃO
A13: 45 | B13: 45763.681 | C13: 45763.682 | D13: rafael.souza@lbx.com.br | E13: Rafael Barbosa Ramalho de Souza | G13: Royal Legacy | H13: 73403 | I13: Não | J13: MONITORAMENTO REMOTO | L13: Aditivo de Contrato | M13: CT/1470171 | N13: NÃO
A14: 46 | B14: 45763.699 | C14: 45763.699 | D14: rafael.souza@lbx.com.br | E14: Rafael Barbosa Ramalho de Souza | G14: Royal Legacy | H14: 73408 | I14: Não | J14: SERVICO DE DRYWALL | L14: Aditivo de Contrato | M14: CS/1470031 | N14: NÃO
A15: 47 | B15: 45764.349 | C15: 45764.351 | D15: rafael.souza@lbx.com.br | E15: Rafael Barbosa Ramalho de Souza | G15: Royal Legacy | H15: 73400 | I15: Sim | J15: INSTALAÇÃO DE REVESTIMENTO CERAMICO E CHECKLIST | L15: Elaboração de Contrato novo | O15: 11255 | P15: E. DA ROCHA | Q15: 45748 | R15: 45838 | S15: https://lbxconstrucao-my.sharepoint.com/personal/lucas_silva_lbx_com_br/Documents/Aplicativos/Microsoft%20Forms/Regulariza%C3%A7%C3%A3o%20de%20contratos%20Sienge%201/Pergunta/NF%20174%20-%20ROYAL%20PLAZA%20INCORPORADORA%20E%20CONSTRUT_Rafael%20Barbosa%20Ramal.pdf | T15: Normal | V15: NÃO
A16: 48 | B16: 45764.697 | C16: 45764.699 | D16: guilherme.aoyama@lbx.com.br | E16: Guilherme Aoyama | G16: Forte de Arundel | H16: 73437 | I16: Sim | J16: Forma e desforma laje lazer cintamento | L16: Aditivo de Contrato | M16: CS/2550026
A17: 49 | B17: 45764.715 | C17: 45764.719 | D17: matheus.pereira@lbx.com.br | E17: Matheus Felipe Pereira | G17: Forte de Arundel | H17: 73139 | I17: Sim | J17: Serviço de manutenção cabo das câmeras rompido | L17: Aditivo de Contrato | M17: CS/2550016
A18: 50 | B18: 45769.632 | C18: 45769.632 | D18: rafael.souza@lbx.com.br | E18: Rafael Barbosa Ramalho de Souza | G18: Royal Legacy | H18: 73574 | I18: Não | J18: PINTURA | L18: Aditivo de Contrato | M18: CS/1470027 | N18: NÃO
A19: 51 | B19: 45770.333 | C19: 45770.334 | D19: rafael.souza@lbx.com.br | E19: Rafael Barbosa Ramalho de Souza | G19: Royal Legacy | H19: 73621 | I19: Não | J19: PINTURA | L19: Aditivo de Contrato | M19: CS/1470098 | N19: NÃO
A20: 52 | B20: 45770.376 | C20: 45770.376 | D20: rafael.souza@lbx.com.br | E20: Rafael Barbosa Ramalho de Souza | G20: Royal Legacy | H20: 73631 | I20: Não | J20: CHECKLIST | L20: Aditivo de Contrato | M20: CT/1470225 | N20: NÃO
A21: 53 | B21: 45770.405 | C21: 45770.406 | D21: rafael.souza@lbx.com.br | E21: Rafael Barbosa Ramalho de Souza | G21: Royal Legacy | H21: 73634 | I21: Não | J21: ASSENTAMENTO DE REVESTIMENTO | L21: Aditivo de Contrato | M21: CS/1470125 | N21: NÃO
A22: 54 | B22: 45770.408 | C22: 45770.409 | D22: leonardo.gottardo@lbx.com.br | E22: Leonardo Pientencoski Gottardo | G22: Forte dos Lagos | H22: 73614 | I22: Não | J22: Limpeza de caixas de agua - 9un | L22: Elaboração de Contrato novo | O22: 16488 | P22: AQUABRAS COMERCIO E MANUTENCAO DE EQUIPAMENTOS PARA TRATAMENTO DE AGUA LTDA | Q22: 45768 | R22: 45775 | S22: https://lbxconstrucao-my.sharepoint.com/personal/lucas_silva_lbx_com_br/Documents/Aplicativos/Microsoft%20Forms/Regulariza%C3%A7%C3%A3o%20de%20contratos%20Sienge%201/Pergunta/NF%20LBX%20(5)_Leonardo%20Pientencosk.pdf | T22: Spot
A23: 55 | B23: 45770.413 | C23: 45770.415 | D23: rafael.souza@lbx.com.br | E23: Rafael Barbosa Ramalho de Souza | G23: Royal Legacy | H23: 73639 | I23: Não | J23: PINTURA | L23: Aditivo de Contrato | M23: CT/1470222
A24: 56 | B24: 45770.567 | C24: 45770.567 | D24: rafael.souza@lbx.com.br | E24: Rafael Barbosa Ramalho de Souza | G24: Royal Legacy | H24: 73554 | I24: Sim | J24: POS FORMA | L24: Aditivo de Contrato | M24: CT/1470167 | N24: NÃO
A25: 57 | B25: 45770.688 | C25: 45770.689 | D25: rafael.souza@lbx.com.br | E25: Rafael Barbosa Ramalho de Souza | G25: Royal Legacy | H25: 73685 | I25: Não | J25: ELETRICA/HIDRAULICA | L25: Aditivo de Contrato | M25: CS/1470084 | N25: NÃO
A26: 58 | B26: 45770.736 | C26: 45770.736 | D26: rafael.souza@lbx.com.br | E26: Rafael Barbosa Ramalho de Souza | G26: Royal Legacy | H26: 73699 | I26: Não | J26: maquinas e equipamentos | L26: Aditivo de Contrato | M26: CS/1470075 | N26: não
A27: 59 | B27: 45771.323 | C27: 45771.325 | D27: rafael.souza@lbx.com.br | E27: Rafael Barbosa Ramalho de Souza | G27: Royal Legacy | H27: 73707 | I27: Não | J27: PINTURA GRADIL | L27: Aditivo de Contrato | M27: CS/1470033 | N27: NÃO
A28: 67 | B28: 45771.552 | C28: 45771.558 | D28: maria.santos@lbx.com.br | E28: Maria Angélica Garcia dos Santos | G28: Royal Ellus | H28: 73727 | I28: Sim | J28: Serviço de Instalação Elétrica | L28: Aditivo de Contrato | M28: CS/1070100
A29: 68 | B29: 45771.558 | C29: 45771.559 | D29: maria.santos@lbx.com.br | E29: Maria Angélica Garcia dos Santos | G29: Royal Ellus | H29: 73728 | I29: Sim | J29: Serviço de Instalação Elétrica | L29: Aditivo de Contrato | M29: CS/1070100
A30: 69 | B30: 45771.559 | C30: 45771.56 | D30: maria.santos@lbx.com.br | E30: Maria Angélica Garcia dos Santos | G30: Royal Ellus | H30: 73635 | I30: Sim | J30: Serviço de Instalação de Elétrica | L30: Aditivo de Contrato | M30: CS/1070100
A31: 70 | B31: 45771.592 | C31: 45771.592 | D31: rafael.souza@lbx.com.br | E31: Rafael Barbosa Ramalho de Souza | G31: Royal Legacy | H31: 73744 | I31: Não | J31: ALVENARIA | L31: Aditivo de Contrato | M31: CT/1470234 | N31: NÃO
A32: 71 | B32: 45771.647 | C32: 45771.648 | D32: rafael.souza@lbx.com.br | E32: Rafael Barbosa Ramalho de Souza | G32: Royal Legacy | H32: 73769 | I32: Não | J32: CHECKLIST E LIMPEZA | L32: Aditivo de Contrato | M32: CS/1470136 | N32: NÃO
A33: 72 | B33: 45772.551 | C33: 45772.582 | D33: emidio.neto@lbx.com.br | E33: Emídio de Sousa Estrela Neto | G33: Royal Porto dourado | H33: 71348 | I33: Sim | J33: Criação de Contrato de Alojamento | L33: Elaboração de Contrato novo | O33: 16517 | P33: Locação de Imóveis | Q33: 45726 | R33: 46171 | S33: https://lbxconstrucao-my.sharepoint.com/personal/lucas_silva_lbx_com_br/Documents/Aplicativos/Microsoft%20Forms/Regulariza%C3%A7%C3%A3o%20de%20contratos%20Sienge%201/Pergunta/Boleto%20Imobiliaria%20Uni%C3%A3o_Em%C3%ADdio%20de%20Sousa%20Estr.pdf | T33: Normal
A34: 73 | B34: 45772.634 | C34: 45772.634 | D34: hugo.silva@lbx.com.br | E34: Hugo Leonardo Oliveira da Silva | G34: Terra de Santa Cruz Unificado Maringá | H34: 73714 | I34: Sim | J34: Serviço de instalações elétricas | L34: Aditivo de Contrato | M34: CT/1010071
A35: 74 | B35: 45775.663 | C35: 45775.663 | D35: rafael.souza@lbx.com.br | E35: Rafael Barbosa Ramalho de Souza | G35: Royal Legacy | H35: 73460 | I35: Sim | J35: PINTURA | L35: Aditivo de Contrato | M35: CS/1470027 | N35: não
A36: 75 | B36: 45775.712 | C36: 45775.714 | D36: isabela.goncalves@lbx.com.br | E36: Isabela Adario Gonçales | G36: Royal Ellus | H36: 73671 | I36: Sim | J36: DESPESAS COM DESLOCAMENTO DE TERCEIRO PARA REALIZACAO DE SERVICOS (OBRA) | L36: Aditivo de Contrato | M36: CS/1070055
A37: 76 | B37: 45775.714 | C37: 45775.722 | D37: isabela.goncalves@lbx.com.br | E37: Isabela Adario Gonçales | G37: Royal Ellus | H37: SC 73904 | I37: Não | J37: LIMPEZA | L37: Aditivo de Contrato | M37: CT/1070163
A38: 78 | B38: 45778.383 | C38: 45778.386 | D38: maria.santos@lbx.com.br | E38: Maria Angélica Garcia dos Santos | G38: Royal Ellus | H38: 73839 | I38: Sim | J38: Serviço de Vigilância Remota Mensal | L38: Aditivo de Contrato | M38: CT/1070099
A39: 81 | B39: 45779.687 | C39: 45779.688 | D39: rafael.souza@lbx.com.br | E39: Rafael Barbosa Ramalho de Souza | G39: Royal Legacy | H39: 74229 | I39: Não | J39: ARGAMASSA ESTABILIZADA | L39: Aditivo de Contrato | M39: CS/1470053 | N39: NÃO
A40: 82 | B40: 45782.451 | C40: 45782.453 | D40: maria.santos@lbx.com.br | E40: Maria Angélica Garcia dos Santos | G40: Royal Ellus | H40: 73838 | I40: Sim | J40: Serviço de Instalação de bomba para Incêndio e Serviço de Instalação Eletrica/Hidraulica para Bombas/Sistema para Reservatório Elevado/Castelo | L40: Aditivo de Contrato | M40: CS/1070090
A41: 83 | B41: 45783.635 | C41: 45783.636 | D41: rafael.souza@lbx.com.br | E41: Rafael Barbosa Ramalho de Souza | G41: Royal Legacy | H41: 74481 | I41: Não | J41: CONCRETO | L41: Aditivo de Contrato | M41: CT/1470200 | N41: NÃO
A42: 84 | B42: 45783.675 | C42: 45783.676 | D42: rafael.souza@lbx.com.br | E42: Rafael Barbosa Ramalho de Souza | G42: Royal Legacy | H42: 74497 | I42: Não | J42: PINTURA | L42: Aditivo de Contrato | M42: CT/1470231 | N42: NÃO
A43: 85 | B43: 45784.39 | C43: 45784.416 | D43: leonardo.gottardo@lbx.com.br | E43: Leonardo Pientencoski Gottardo | G43: Duo Ville Residence | H43: 73989 | I43: Sim | J43: Laudo cautelar de vizinhança | L43: Elaboração de Contrato novo | O43: 15701 | P43: AFONSO ARQUITETURA, PLANEJAMENTO E CONSTRUCAO LTDA | Q43: 45778 | R43: 45869 | S43: https://lbxconstrucao-my.sharepoint.com/personal/lucas_silva_lbx_com_br/Documents/Aplicativos/Microsoft%20Forms/Regulariza%C3%A7%C3%A3o%20de%20contratos%20Sienge%201/Pergunta/NOTA%20FISCAL%20RE-ELABOR%C3%87%C3%83O%20DO%20LAUDO%20EM%20PARANAVA_Leonardo%20Pientencosk.pdf | T43: Spot
A44: 86 | B44: 45784.66 | C44: 45784.661 | D44: rafael.souza@lbx.com.br | E44: Rafael Barbosa Ramalho de Souza | G44: Royal Legacy | H44: 74606 | I44: Não | J44: LOCAÇÃO DE MAQUINAS E EQP | L44: Aditivo de Contrato | M44: CS/1470044 | N44: NÃO
A45: 87 | B45: 45785.515 | C45: 45785.515 | D45: kevin.silva@lbx.com.br | E45: Kevin Brian da Silva | G45: Royal Paradise | H45: 74326 | I45: Sim | J45: SERVICO DE PERFURACAO DE ESTACA ESCAVADA DN 30 CM | L45: Elaboração de Contrato novo | O45: 16426 | P45: CORREA FUNDACOES LTDA | Q45: 45785 | R45: 46150 | S45: https://lbxconstrucao-my.sharepoint.com/personal/lucas_silva_lbx_com_br/Documents/Aplicativos/Microsoft%20Forms/Regulariza%C3%A7%C3%A3o%20de%20contratos%20Sienge%201/Pergunta/NF_Kevin%20Brian%20da%20Silva.pdf | T45: Normal
A46: 88 | B46: 45785.657 | C46: 45785.658 | D46: hugo.silva@lbx.com.br | E46: Hugo Leonardo Oliveira da Silva | G46: Terra de Santa Cruz Unificado Maringá | H46: 74511 | I46: Sim | J46: serviço de pintura externa | L46: Aditivo de Contrato | M46: CS/990097
A47: 89 | B47: 45785.658 | C47: 45785.66 | D47: hugo.silva@lbx.com.br | E47: Hugo Leonardo Oliveira da Silva | G47: Terra de Santa Cruz Unificado Maringá | H47: 74496 | I47: Sim | J47: Serviço de pintura interna | L47: Aditivo de Contrato | M47: CS/990081
A48: 90 | B48: 45785.66 | C48: 45785.662 | D48: hugo.silva@lbx.com.br | E48: Hugo Leonardo Oliveira da Silva | G48: Terra de Santa Cruz Unificado Maringá | H48: 74463 | I48: Sim | J48: Serviço de pintura interna | L48: Aditivo de Contrato | M48: CS/1010072
A49: 91 | B49: 45785.662 | C49: 45785.663 | D49: hugo.silva@lbx.com.br | E49: Hugo Leonardo Oliveira da Silva | G49: Terra de Santa Cruz Unificado Maringá | H49: 74448 | I49: Sim | J49: Serviço de regularização de laje; assentamento de laminado | L49: Aditivo de Contrato | M49: CS/990098
A50: 92 | B50: 45785.663 | C50: 45785.663 | D50: hugo.silva@lbx.com.br | E50: Hugo Leonardo Oliveira da Silva | G50: Terra de Santa Cruz Unificado Maringá | H50: 74494 | I50: Sim | J50: Serviço de regularização de laje; assentamento de piso laminado | L50: Aditivo de Contrato | M50: CS/990066
A51: 93 | B51: 45785.663 | C51: 45785.678 | D51: hugo.silva@lbx.com.br | E51: Hugo Leonardo Oliveira da Silva | G51: Terra de Santa Cruz Unificado Maringá | H51: 74447 | I51: Sim | J51: Serviço de assentamento de kit porta pronta | L51: Aditivo de Contrato | M51: CS/990094
A52: 94 | B52: 45785.678 | C52: 45785.68 | D52: hugo.silva@lbx.com.br | E52: Hugo Leonardo Oliveira da Silva | G52: Terra de Santa Cruz Unificado Maringá | H52: 74523 | I52: Sim | J52: Serviço de instalação elétrica | L52: Aditivo de Contrato | M52: CS/990064
A53: 95 | B53: 45785.68 | C53: 45785.681 | D53: hugo.silva@lbx.com.br | E53: Hugo Leonardo Oliveira da Silva | G53: Terra de Santa Cruz Unificado Maringá | H53: 74525 | I53: Sim | J53: Serviço de instalação elétrica | L53: Aditivo de Contrato | M53: CS/1010071
A54: 96 | B54: 45785.681 | C54: 45785.685 | D54: hugo.silva@lbx.com.br | E54: Hugo Leonardo Oliveira da Silva | G54: Terra de Santa Cruz Unificado Maringá | H54: 74444 | I54: Sim | J54: Serviço de gesso corrido, locação de equipamento e distribuição de material | L54: Aditivo de Contrato | M54: CS/990083
A55: 97 | B55: 45785.685 | C55: 45785.692 | D55: hugo.silva@lbx.com.br | E55: Hugo Leonardo Oliveira da Silva | G55: Terra de Santa Cruz Unificado Maringá | H55: 74450 | I55: Sim | J55: Serviço de civil | L55: Aditivo de Contrato | M55: cs/990042
A56: 98 | B56: 45785.693 | C56: 45785.697 | D56: hugo.silva@lbx.com.br | E56: Hugo Leonardo Oliveira da Silva | G56: Terra de Santa Cruz Unificado Maringá | H56: 74517 | I56: Sim | J56: Serviço de civil | L56: Aditivo de Contrato | M56: CS/990092
A57: 99 | B57: 45785.697 | C57: 45785.697 | D57: hugo.silva@lbx.com.br | E57: Hugo Leonardo Oliveira da Silva | G57: Terra de Santa Cruz Unificado Maringá | H57: 74522 | I57: Sim | J57: Serviço de distribuição de material | L57: Aditivo de Contrato | M57: CT/990215
... A63: 105 | B63: 45785.705 | C63: 45785.706 | D63: hugo.silva@lbx.com.br | E63: Hugo Leonardo Oliveira da Silva | G63: Terra de Santa Cruz Unificado Maringá | H63: 74529 | I63: Sim | J63: Serviço de distribuição de material | L63: Aditivo de Contrato | M63: CT/990211
A64: 106 | B64: 45785.762 | C64: 45785.762 | D64: kevin.silva@lbx.com.br | E64: Kevin Brian da Silva | G64: Royal Paradise | H64: 74467 | I64: Sim | J64: - SERVICO DE ASSENTAMENTO DE BLOCO DE CONCRETO COM EXECUCAO DE VIGA BALDRAME PARA MURO DE FECHAMENTO h=2,20m | L64: Elaboração de Contrato novo | O64: 13660 | P64: EMPREITEIRA P DE OLIVEIRA LTDA | Q64: 45785 | R64: 46150 | S64: https://lbxconstrucao-my.sharepoint.com/personal/lucas_silva_lbx_com_br/Documents/Aplicativos/Microsoft%20Forms/Regulariza%C3%A7%C3%A3o%20de%20contratos%20Sienge%201/Pergunta/NFSE%2030%20TSC%20I%20(LBX)_Kevin%20Brian%20da%20Silva.pdf | T64: Normal
A65: 107 | B65: 45786.457 | C65: 45786.467 | D65: kevin.silva@lbx.com.br | E65: Kevin Brian da Silva | G65: Royal Paradise | H65: 74673 | I65: Sim | J65: SERVICO EXECUCAO ARMACAO CORTE DOBRA MONTAGEM ACO | L65: Elaboração de Contrato novo | O65: 8629 | P65: AMARIUDO FERNANDO DOS SANTOS | Q65: 45786 | R65: 46151 | S65: https://lbxconstrucao-my.sharepoint.com/personal/lucas_silva_lbx_com_br/Documents/Aplicativos/Microsoft%20Forms/Regulariza%C3%A7%C3%A3o%20de%20contratos%20Sienge%201/Pergunta/NFS%20LBX%20-%20PARANAVAI%202_Kevin%20Brian%20da%20Silva.pdf | T65: Normal
A66: 108 | B66: 45789.439 | C66: 45789.44 | D66: rafael.souza@lbx.com.br | E66: Rafael Barbosa Ramalho de Souza | G66: Royal Legacy | H66: 74796 | I66: Não | J66: PINTURA DE VAGAS | L66: Aditivo de Contrato | M66: CS/1470084 | N66: NÃO
A67: 109 | B67: 45790.367 | C67: 45790.371 | D67: matheus.gebara@lbx.com.br | E67: Matheus Farah Gebara | G67: Royal Porto dourado | H67: 73874 | I67: Sim | J67: EXECUÇÃO DE REVESTIMENTO CERÂMICO / REJUNTE / IMPERMEABILIZAÇÃO | L67: Elaboração de Contrato novo | O67: 16450 | P67: KSB EMPREITEIRA LTDA | Q67: 45796 | R67: 46230 | S67: https://lbxconstrucao-my.sharepoint.com/personal/lucas_silva_lbx_com_br/_layouts/15/Doc.aspx?sourcedoc=%7BF6071245-52F6-4D6D-AF68-E4E6DCF9B8AC%7D&file=PLANILHA%20DESCRITIVA%20DE%20SERVI%C3%87OS%20-%20BENTO%20-%20REV_Matheus%20Farah%20Gebara.xlsx&action=default&mobileredirect=true | T67: Normal | V67: o CNPJ é novo desta maneira o fornecedor não emitiu nenhuma nota fiscal referente a este CNPJ ainda, colocar na elaboração do contrato Sienge empreitada de outro município
A68: 110 | B68: 45790.428 | C68: 45790.441 | D68: matheus.gebara@lbx.com.br | E68: Matheus Farah Gebara | G68: Forte de Arundel | H68: 74207 | I68: Sim | J68: Execução de piso polido / capeamento | L68: Elaboração de Contrato novo | O68: 16570 | P68: GV PISOS INDUSTRIAIS LTDA | Q68: 45796 | R68: 45859 | S68: https://lbxconstrucao-my.sharepoint.com/personal/lucas_silva_lbx_com_br/Documents/Aplicativos/Microsoft%20Forms/Regulariza%C3%A7%C3%A3o%20de%20contratos%20Sienge%201/Pergunta/449_Matheus%20Farah%20Gebara.pdf | T68: Spot
A69: 111 | B69: 45790.445 | C69: 45790.447 | D69: matheus.gebara@lbx.com.br | E69: Matheus Farah Gebara | G69: Royal Plaza | H69: 73399 | I69: Sim | J69: Execução de Gesso Liso | L69: Elaboração de Contrato novo | O69: 16376 | P69: ARTE FINAL GESSO E REVESTIMENTO LTDA | Q69: 45789 | R69: 45992 | S69: https://lbxconstrucao-my.sharepoint.com/personal/lucas_silva_lbx_com_br/Documents/Aplicativos/Microsoft%20Forms/Regulariza%C3%A7%C3%A3o%20de%20contratos%20Sienge%201/Pergunta/NFSe%2042%20Mampei%20(2)_Matheus%20Farah%20Gebara.pdf | T69: Normal
A70: 112 | B70: 45790.448 | C70: 45790.449 | D70: matheus.gebara@lbx.com.br | E70: Matheus Farah Gebara | G70: Royal Plaza | H70: 73538 | I70: Sim | J70: Pintura Interna | L70: Elaboração de Contrato novo | O70: 16424 | P70: PINTURAS E L GUERREIROS DE DEUS LTDA | Q70: 45789 | R70: 46055 | S70: https://lbxconstrucao-my.sharepoint.com/personal/lucas_silva_lbx_com_br/Documents/Aplicativos/Microsoft%20Forms/Regulariza%C3%A7%C3%A3o%20de%20contratos%20Sienge%201/Pergunta/NFS%204%20(2)_Matheus%20Farah%20Gebara.pdf | T70: Normal
A71: 113 | B71: 45790.452 | C71: 45790.454 | D71: matheus.gebara@lbx.com.br | E71: Matheus Farah Gebara | G71: Terra de Santa Cruz Unificado Maringá | H71: 74576 | I71: Sim | J71: Pintura Interna | L71: Elaboração de Contrato novo | O71: 8488 | P71: F C S DA COSTA - PINTURAS LTDA | Q71: 45796 | R71: 45992 | S71: https://lbxconstrucao-my.sharepoint.com/personal/lucas_silva_lbx_com_br/Documents/Aplicativos/Microsoft%20Forms/Regulariza%C3%A7%C3%A3o%20de%20contratos%20Sienge%201/Pergunta/219-Square_Matheus%20Farah%20Gebara.pdf | T71: Normal
A72: 114 | B72: 45790.539 | C72: 45790.539 | D72: hugo.silva@lbx.com.br | E72: Hugo Leonardo Oliveira da Silva | G72: Terra de Santa Cruz Unificado Maringá | H72: 74429 | I72: Sim | J72: serviço de execução de gesso corrido | L72: Aditivo de Contrato | M72: CT/990207
A73: 115 | B73: 45790.62 | C73: 45790.621 | D73: maria.santos@lbx.com.br | E73: Maria Angélica Garcia dos Santos | G73: Royal Ellus | H73: 74753 | I73: Sim | J73: Vigilância | L73: Aditivo de Contrato | M73: CT/1070099
A74: 116 | B74: 45790.677 | C74: 45790.677 | D74: hugo.silva@lbx.com.br | E74: Hugo Leonardo Oliveira da Silva | G74: Terra de Santa Cruz Unificado Maringá | H74: 74393 | I74: Sim | J74: Serviço de execução de instalações elétricas | L74: Aditivo de Contrato | M74: CS/990090
A75: 117 | B75: 45790.69 | C75: 45790.692 | D75: beatriz.oliveira@lbx.com.br | E75: Beatriz da Silva de Oliveira | G75: Royal Ellus | H75: 74687 | I75: Sim | J75: RESSERVICO DE FECHAMENTO DE PAREDE EM DRYWALL | L75: Aditivo de Contrato | M75: CS/1070076
A76: 118 | B76: 45790.692 | C76: 45790.693 | D76: beatriz.oliveira@lbx.com.br | E76: Beatriz da Silva de Oliveira | G76: Royal Ellus | H76: 74738 | I76: Sim | J76: RESSERVIÇO DE ELÉTRICA E HIDRAULICA | L76: Aditivo de Contrato | M76: CT/1070117
A77: 119 | B77: 45790.693 | C77: 45790.694 | D77: beatriz.oliveira@lbx.com.br | E77: Beatriz da Silva de Oliveira | G77: Royal Ellus | H77: 74824 | I77: Sim | J77: RESSERVICO DE FECHAMENTO DE PAREDE EM DRYWALL | L77: Aditivo de Contrato | M77: CS/1070114
A78: 120 | B78: 45790.709 | C78: 45790.714 | D78: isabela.goncalves@lbx.com.br | E78: Isabela Adario Gonçales | G78: Royal Ellus | H78: 74811 | I78: Sim | J78: SERVICO DE EXECUCAO DE FORRO DE GESSO COM SANCA DE LED - MATERIAL E MAO DE OBRA | L78: Aditivo de Contrato | M78: CT/1070160
A79: 121 | B79: 45790.714 | C79: 45790.715 | D79: isabela.goncalves@lbx.com.br | E79: Isabela Adario Gonçales | G79: Royal Ellus | H79: 74820 | I79: Sim | J79: RESSERVICO DE PINTURA INTERNA | L79: Aditivo de Contrato | M79: CT/1070158
A80: 122 | B80: 45790.715 | C80: 45790.716 | D80: isabela.goncalves@lbx.com.br | E80: Isabela Adario Gonçales | G80: Royal Ellus | H80: 74822 | I80: Não | J80: SERVICO EXECUCAO CHECK LIST FINAL | L80: Aditivo de Contrato | M80: CS/1070113
A81: 123 | B81: 45790.716 | C81: 45790.717 | D81: isabela.goncalves@lbx.com.br | E81: Isabela Adario Gonçales | G81: Royal Ellus | H81: 74823 | I81: Sim | J81: RESSERVICO DE FECHAMENTO DE PAREDE EM DRYWALL | L81: Aditivo de Contrato | M81: CT/1070160
A82: 124 | B82: 45790.717 | C82: 45790.717 | D82: isabela.goncalves@lbx.com.br | E82: Isabela Adario Gonçales | G82: Royal Ellus | H82: 74904 | I82: Não | J82: SERVICO EXECUCAO LIMPEZA HALL | L82: Aditivo de Contrato | M82: CT/1070163
A83: 125 | B83: 45791.429 | C83: 45791.432 | D83: hugo.silva@lbx.com.br | E83: Hugo Leonardo Oliveira da Silva | G83: Terra de Santa Cruz Unificado Maringá | H83: 00000 | I83: Sim | J83: Serviço de execução de controle tecnológico do concreto | L83: Aditivo de Contrato | M83: CS/1010100 | N83: ALTERAR O SEGUINTE ITEM DO CONTRATO: 00.000.000.005 -13893 -CONTROLE TECNOLOGICO - ROMPIMENTO DE CORPO DE PROVA - POR M3 300,0000 m3. ALTERAÇÃO: Aumentar o preço da mão de obra de R$24,00/m³ para R$36,00/m³
A84: 126 | B84: 45792.443 | C84: 45792.445 | D84: giovanna.tomitam@lbx.com.br | E84: Giovanna Trevisan Tomitam | G84: Royal Plaza | H84: 74845 | I84: Não | J84: Pintura interna | L84: Elaboração de Contrato novo | O84: 13832 | P84: GILIARDY MARTINS DA SILVA | Q84: 45803 | R84: 46142 | S84: https://lbxconstrucao-my.sharepoint.com/personal/lucas_silva_lbx_com_br/Documents/Aplicativos/Microsoft%20Forms/Regulariza%C3%A7%C3%A3o%20de%20contratos%20Sienge%201/Pergunta/Giliardy%20NFS-e_110_30_04_2025%20m%20cedros_Giovanna%20Trevisan%20To.pdf | T84: Normal
A85: 127 | B85: 45792.453 | C85: 45792.454 | D85: rafael.souza@lbx.com.br | E85: Rafael Barbosa Ramalho de Souza | G85: Royal Legacy | H85: 75014 | I85: Não | J85: PINTURA | L85: Aditivo de Contrato | M85: CT/1470222 | N85: NÃO
A86: 128 | B86: 45793.333 | C86: 45793.336 | D86: matheus.gebara@lbx.com.br | E86: Matheus Farah Gebara | G86: Terra de Santa Cruz Unificado Maringá | H86: SC 75030 | I86: Não | J86: Pintura Interna | L86: Elaboração de Contrato novo | O86: 13191 | P86: RODRIGO LAIA SANTOS | Q86: 45803 | R86: 45988 | S86: https://lbxconstrucao-my.sharepoint.com/personal/lucas_silva_lbx_com_br/Documents/Aplicativos/Microsoft%20Forms/Regulariza%C3%A7%C3%A3o%20de%20contratos%20Sienge%201/Pergunta/Emissa%26%23771;o%20NFS-42_%20RODRIGO%20LAIA%20SANTOS_Matheus%20Farah%20Gebara.pdf | T86: Normal
A87: 129 | B87: 45793.407 | C87: 45793.407 | D87: isabela.goncalves@lbx.com.br | E87: Isabela Adario Gonçales | G87: Royal Ellus | H87: 74973 | I87: Sim | J87: RESSERVICO DE FECHAMENTO DE PAREDE EM DRYWALL | L87: Aditivo de Contrato | M87: CT/1070160
A88: 130 | B88: 45793.568 | C88: 45793.577 | D88: matheus.gebara@lbx.com.br | E88: Matheus Farah Gebara | G88: Royal Park Forest | H88: 74302 | I88: Sim | J88: Instalações Hidráulicas - Torre | L88: Elaboração de Contrato novo | O88: 16219 | P88: R.M INSTALAÇOES E MANUTENÇÕES LTDA | Q88: 45796 | R88: 46203 | S88: https://lbxconstrucao-my.sharepoint.com/personal/lucas_silva_lbx_com_br/Documents/Aplicativos/Microsoft%20Forms/Regulariza%C3%A7%C3%A3o%20de%20contratos%20Sienge%201/Pergunta/4d870a31-d827-433c-bfae-d563db96253b_Matheus%20Farah%20Gebara.pdf | T88: Normal | V88: Planilha com os valores enviada via Teams
A89: 131 | B89: 45793.583 | C89: 45793.584 | D89: rafael.souza@lbx.com.br | E89: Rafael Barbosa Ramalho de Souza | G89: Royal Legacy | H89: 75142 | I89: Não | J89: LIMPEZA | L89: Aditivo de Contrato | M89: CS/1470136 | N89: NÃO
A90: 132 | B90: 45793.581 | C90: 45793.585 | D90: matheus.gebara@lbx.com.br | E90: Matheus Farah Gebara | G90: Royal Park Forest | H90: 74297 | I90: Sim | J90: Instalações Elétricas - Torre | L90: Elaboração de Contrato novo | O90: 13626 | P90: E. VIEIRA E GUILHERME LTDA | Q90: 45796 | R90: 46203 | S90: https://lbxconstrucao-my.sharepoint.com/personal/lucas_silva_lbx_com_br/Documents/Aplicativos/Microsoft%20Forms/Regulariza%C3%A7%C3%A3o%20de%20contratos%20Sienge%201/Pergunta/NF%20MODELO%20E%20VIEIRA%20E%20GUILHERME%20LTDA_Matheus%20Farah%20Gebara.pdf | T90: Normal | V90: Valores foram enviados via Teams
A91: 133 | B91: 45793.602 | C91: 45793.602 | D91: rafael.souza@lbx.com.br | E91: Rafael Barbosa Ramalho de Souza | G91: Royal Legacy | H91: 75152 | I91: Não | J91: PINTURA | L91: Aditivo de Contrato | M91: CS/1470027 | N91: NÃO
A92: 134 | B92: 45793.612 | C92: 45793.613 | D92: rafael.souza@lbx.com.br | E92: Rafael Barbosa Ramalho de Souza | G92: Royal Legacy | H92: 75159 | I92: Não | J92: INST. DE REVESTIMENTO CERAMICO | L92: Aditivo de Contrato | M92: CS/1470125 | N92: NÃO
A93: 135 | B93: 45793.651 | C93: 45793.651 | D93: beatriz.oliveira@lbx.com.br | E93: Beatriz da Silva de Oliveira | G93: Royal Ellus | H93: 74948 | I93: Sim | J93: RESSERVICO DE PORTA DE MADEIRA | L93: Aditivo de Contrato | M93: CS/1070076
A94: 136 | B94: 45793.652 | C94: 45793.653 | D94: beatriz.oliveira@lbx.com.br | E94: Beatriz da Silva de Oliveira | G94: Royal Ellus | H94: 74893 | I94: Sim | J94: SERVICO EXECUCAO CHECK LIST FINAL | L94: Aditivo de Contrato | M94: CS/1070091
A95: 137 | B95: 45794.396 | C95: 45794.397 | D95: rafael.souza@lbx.com.br | E95: Rafael Barbosa Ramalho de Souza | G95: Royal Legacy | H95: 75188 | I95: Não | J95: ASSENTAMENTO DE PAVER | L95: Aditivo de Contrato | M95: CS/1470057 - JSM | N95: NÃO
A96: 138 | B96: 45794.434 | C96: 45794.434 | D96: rafael.souza@lbx.com.br | E96: Rafael Barbosa Ramalho de Souza | G96: Royal Legacy | H96: 75190 | I96: Não | J96: CAÇAMBA | L96: Aditivo de Contrato | M96: CS/1470128 | N96: NÃO
A97: 139 | B97: 45796.58 | C97: 45796.58 | D97: isabela.goncalves@lbx.com.br | E97: Isabela Adario Gonçales | G97: Royal Ellus | H97: 75221 | I97: Não | J97: ajuda de custo | L97: Aditivo de Contrato | M97: CT/1070158
A98: 140 | B98: 45796.58 | C98: 45796.581 | D98: isabela.goncalves@lbx.com.br | E98: Isabela Adario Gonçales | G98: Royal Ellus | H98: SC 75240 | I98: Não | J98: resserviço parede de drywall | L98: Aditivo de Contrato | M98: CT/1070170
A99: 141 | B99: 45796.593 | C99: 45796.594 | D99: rafael.souza@lbx.com.br | E99: Rafael Barbosa Ramalho de Souza | G99: Royal Legacy | H99: 75237 | I99: Não | J99: INST. DRYWALL | L99: Aditivo de Contrato | M99: CS/1470031 | N99: NÃO
A100: 142 | B100: 45796.602 | C100: 45796.603 | D100: beatriz.oliveira@lbx.com.br | E100: Beatriz da Silva de Oliveira | G100: Royal Ellus | H100: 75164 | I100: Sim | J100: SERVICO EXECUCAO PINTURA EXT/INT TEXTURA PROJETADA | L100: Aditivo de Contrato | M100: CS/1070021
A101: 143 | B101: 45796.603 | C101: 45796.604 | D101: beatriz.oliveira@lbx.com.br | E101: Beatriz da Silva de Oliveira | G101: Royal Ellus | H101: 75009 | I101: Sim | J101: PINTURA HALL | L101: Aditivo de Contrato | M101: CS/1070042
A102: 144 | B102: 45796.604 | C102: 45796.605 | D102: beatriz.oliveira@lbx.com.br | E102: Beatriz da Silva de Oliveira | G102: Royal Ellus | H102: 75012 | I102: Sim | J102: PINTURA DE HALL | L102: Aditivo de Contrato | M102: CS/1070042
A103: 145 | B103: 45796.695 | C103: 45796.696 | D103: giovanna.tomitam@lbx.com.br | E103: Giovanna Trevisan Tomitam | G103: Royal Plaza | H103: 75224 | I103: Sim | J103: muro de arrimo | L103: Aditivo de Contrato | M103: CT/2420097
A104: 146 | B104: 45796.706 | C104: 45796.708 | D104: giovanna.tomitam@lbx.com.br | E104: Giovanna Trevisan Tomitam | G104: Royal Plaza | H104: 75238 | I104: Sim | J104: CONTROLE TECNOLOGICO | L104: Aditivo de Contrato | M104: CS/2420039
A105: 147 | B105: 45796.708 | C105: 45796.708 | D105: giovanna.tomitam@lbx.com.br | E105: Giovanna Trevisan Tomitam | G105: Royal Plaza | H105: 75235 | I105: Sim | J105: CONTROLE TECNOLOGICO | L105: Aditivo de Contrato | M105: CS/2420042
...

Sheet Especificação
A1: Obra | B1: Coordenador | C1: Fornecedor | D1: Insumo | E1: Data | F1: ValorTotal
A2: PORTO RICO - NEO WAVE | B2: Flavia Shigueoka | C2: RIO DEPOSITO DE MATERIAIS PARA CONSTRUCAO LTDA | D2: DISCO DE CORTE PARA FERRO | E2: 46149 | F2: 280.958
A3: MARINGA - FORTE DE ATHENA | B3: Lucas Gaspar | C3: F.B. LOMBARDI - FERRAGENS | D3: MATERIAL PARA EXECUCAO DE SERVICO | E3: 46149 | F3: 576.4
A4: MARINGA - FORTE DE ATHENA | B4: Lucas Gaspar | C4: COMERCIAL DE FERRAGENS COFEBRAL LTDA | D4: PARAFUSADEIRA FURADEIRA BOSCH GSB 180-LI 18V C/2 BATERIAS +1 CARREG. +1 MALETA | E4: 46149 | F4: 1254
A5: MARINGA - FORTE DE ATHENA | B5: Lucas Gaspar | C5: COMERCIAL DE FERRAGENS COFEBRAL LTDA | E5: 46149
A6: CASCAVEL - DUO VILLE RESIDENCE | B6: Diego Gomes | C6: OMORI E SUZAKI CASCAVEL ALUGUEL DE EQUIPAMENTOS LTDA. | D6: LOCACAO TRAVA DIAGONAL PARA ANDAIME | E6: 46149 | F6: 12
A7: CASCAVEL - DUO VILLE RESIDENCE | B7: Diego Gomes | C7: OMORI E SUZAKI CASCAVEL ALUGUEL DE EQUIPAMENTOS LTDA. | D7: LOCACAO PAINEL METALICO PARA ANDAIME | E7: 46149 | F7: 360
A8: CASCAVEL - DUO VILLE RESIDENCE | B8: Diego Gomes | C8: OMORI E SUZAKI CASCAVEL ALUGUEL DE EQUIPAMENTOS LTDA. | D8: LOCACAO SAPATA PARA ANDAIME | E8: 46149 | F8: 280
A9: CASCAVEL - DUO VILLE RESIDENCE | B9: Diego Gomes | C9: OMORI E SUZAKI CASCAVEL ALUGUEL DE EQUIPAMENTOS LTDA. | D9: LOCACAO PISO PLATAFORMA PARA ANDAIME | E9: 46149 | F9: 11
A10: CASCAVEL - DUO VILLE RESIDENCE | B10: Diego Gomes | C10: OMORI E SUZAKI CASCAVEL ALUGUEL DE EQUIPAMENTOS LTDA. | D10: LOCACAO DE ANDAIME MULTIDIRECIONAL | E10: 46149 | F10: 217
A11: CASCAVEL - DUO VILLE RESIDENCE | B11: Diego Gomes | C11: OMORI E SUZAKI CASCAVEL ALUGUEL DE EQUIPAMENTOS LTDA. | D11: LOCACAO DE ANDAIME MULTIDIRECIONAL | E11: 46149 | F11: 708
A12: CASCAVEL - DUO VILLE RESIDENCE | B12: Diego Gomes | C12: OMORI E SUZAKI CASCAVEL ALUGUEL DE EQUIPAMENTOS LTDA. | D12: LOCACAO PISO PLATAFORMA PARA ANDAIME | E12: 46149 | F12: 216
A13: PAIÇANDU - TERRA DE SANTA CRUZ | B13: Flavia Shigueoka | C13: MADEFORT MARINGA COMERCIO DE MADEIRAS EIRELI ME | D13: CAIBRO DE PINUS 5X5X1,0MT (ESTACA) | E13: 46149 | F13: 240
A14: PAIÇANDU - TERRA DE SANTA CRUZ | B14: Flavia Shigueoka | C14: ELETRONORTE MARINGA COM. FERRAMENTAS E SERVIÇOS | D14: SERVICO DE MANUTENCAO DE MAQUINAS E EQUIPAMENTOS | E14: 46149 | F14: 619
A15: PAIÇANDU - TERRA DE SANTA CRUZ | B15: Flavia Shigueoka | C15: ERICA KUMIKO OTA LOCACAO DE ANDAIMES LTDA | D15: LOCACAO DE ANDAIME TUBULAR | E15: 46149 | F15: 2234
A16: PARANAVAI - TERRA DE SANTA CRUZ II | B16: Flavia Shigueoka | C16: MARIA SONIA DOS REIS DE OLIVEIRA 48872784972 | D16: ACOES DE ENGAJAMENTO | E16: 46149 | F16: 655
A17: CASCAVEL - ROYAL PLAZA | B17: Eduardo Marques | C17: DGM COMERCIO DE UTILIDADES DOMÉSTICAS - EIRELI | D17: LOCACAO DE COMPACTADOR (SAPO) | E17: 46149 | F17: 1600
... A126: CASCAVEL - DUO VILLE RESIDENCE | B126: Diego Gomes | C126: EDFASS LIVRARIA E PAPELARIA LTDA | D126: CANETA PARA QUADRO BRANCO | E126: 46147 | F126: 14.7
A127: MARINGA - FORTE DE ATHENA | B127: Lucas Gaspar | C127: BR ENGENHARIA E OBRAS DE INFRAESTRUTURA LTDA | E127: 46147
A128: CASCAVEL - ROYAL PLAZA | B128: Eduardo Marques | C128: BIGOLIN MATERIAIS DE CONSTRUCAO LTDA | D128: ROLO PARA PINTURA | E128: 46147 | F128: 25.88
A129: CASCAVEL - ROYAL PLAZA | B129: Eduardo Marques | C129: BIGOLIN MATERIAIS DE CONSTRUCAO LTDA | D129: PINO ENGATE MACHO 1/4"&#148; | E129: 46147 | F129: 59.74
A130: CASCAVEL - ROYAL PLAZA | B130: Eduardo Marques | C130: BIGOLIN MATERIAIS DE CONSTRUCAO LTDA | D130: VALVULA PARA MICTORIO | E130: 46147 | F130: 398.1702
A131: ARAPONGAS - ROYAL PARADISE | B131: Gustavo Sana | C131: M F - EQUIPAMENTOS DE PROTECAO INDIVIDUAL E COLETIVO LTDA | D131: LUVA DE VAQUETA MISTA TAMANHO 7 | E131: 46147 | F131: 990
A132: ARAPONGAS - ROYAL PARADISE | B132: Gustavo Sana | C132: 65.707.166 FELIPE PORTILHO LOPES | D132: LANCHE/CAFE/REFEICAO EM OBRA | E132: 46147 | F132: 12255
A133: CASCAVEL - ROYAL PLAZA | B133: Eduardo Marques | C133: BIGOLIN MATERIAIS DE CONSTRUCAO LTDA | D133: ARGAMASSA COLANTE AC - II | E133: 46147 | F133: 2729.8
A134: CASCAVEL - DUO VILLE RESIDENCE | B134: Diego Gomes | C134: EDFASS LIVRARIA E PAPELARIA LTDA | D134: ISOPOR 1000X100X10MM | E134: 46147 | F134: 75
A135: CASCAVEL - ROYAL PLAZA | B135: Eduardo Marques | C135: BIGOLIN MATERIAIS DE CONSTRUCAO LTDA | D135: TUBO PVC ESGOTO PL 200MM | E135: 46147 | F135: 2180.54
A136: CASCAVEL - ROYAL PLAZA | B136: Eduardo Marques | C136: BIGOLIN MATERIAIS DE CONSTRUCAO LTDA | D136: MATERIAL PARA EXECUCAO SERVIÇO DE DRYWALL | E136: 46147 | F136: 697.5969
A137: CASCAVEL - ROYAL PLAZA | B137: Eduardo Marques | C137: BIGOLIN MATERIAIS DE CONSTRUCAO LTDA | D137: FILME DE PROTECAO ELETROSTATICO AUTO COLANTE 2,4M X 20M | E137: 46147 | F137: 1042.29
A138: CASCAVEL - DUO VILLE RESIDENCE | B138: Diego Gomes | C138: EDFASS LIVRARIA E PAPELARIA LTDA | D138: CANETA PARA QUADRO BRANCO | E138: 46147 | F138: 6.6
A139: CASCAVEL - DUO VILLE RESIDENCE | B139: Diego Gomes | C139: EDFASS LIVRARIA E PAPELARIA LTDA | D139: CANETA PARA QUADRO BRANCO | E139: 46147 | F139: 14.7
A140: CASCAVEL - ROYAL PLAZA | B140: Eduardo Marques | C140: BIGOLIN MATERIAIS DE CONSTRUCAO LTDA | D140: PINCEL PARA PINTURA | E140: 46147 | F140: 216.91
A141: CASCAVEL - ROYAL PLAZA | B141: Eduardo Marques | C141: BIGOLIN MATERIAIS DE CONSTRUCAO LTDA | E141: 46147
A142: CASCAVEL - ROYAL PLAZA | B142: Eduardo Marques | C142: BIGOLIN MATERIAIS DE CONSTRUCAO LTDA | D142: THINNER FORTE | E142: 46147 | F142: 358.09
A143: MARINGA - FORTE DE ATHENA | B143: Lucas Gaspar | C143: L. LOPES DE MORAES - COMERCIO DE FERRAMENTAS | D143: LOCACAO DE CAMINHAO MUNCK | E143: 46146 | F143: 2200
A144: MARINGA - FORTE DE ATHENA | B144: Lucas Gaspar | C144: L. LOPES DE MORAES - COMERCIO DE FERRAMENTAS | D144: LOCACAO DE CAMINHAO MUNCK | E144: 46146 | F144: 1650
A145: MARINGA - FORTE DE ATHENA | B145: Lucas Gaspar | C145: L. LOPES DE MORAES - COMERCIO DE FERRAMENTAS | D145: DESPESA COM DESLOCAMENTO DE MAQUINAS E EQUIPAMENTOS LOCADOS - DO FORNECEDOR ATE A OBRA | E145: 46146 | F145: 660
A146: MARINGA - FORTE DE ATHENA | B146: Lucas Gaspar | C146: WESLEY FERREIRA SILVA 07826489911 | E146: 46146
A147: TOLEDO - ROYAL PARK FOREST | B147: Diego Gomes | C147: MESTRE DA OBRA TOLEDO | D147: LOCACAO LIXADEIRA DE PAREDE / TETO TELESCOPICA 220V | E147: 46146 | F147: 390
A148: MARINGA - TERRA DE SANTA CRUZ II | C148: CF MARINGA ALUGUEL DE EQUIPAMENTOS E COMERCIO DE MAQUINAS LT | D148: LOCACAO BOMBA SUBMERSA DE SUCCAO | E148: 46146 | F148: 150
A149: TOLEDO - ROYAL PARK FOREST | B149: Diego Gomes | C149: KLAIS E SILVA LOCACAO DE EMPILHADEIRAS LTDA | D149: DESPESA COM DESLOCAMENTO DE MAQUINAS E EQUIPAMENTOS LOCADOS - DO FORNECEDOR ATE A OBRA | E149: 46146 | F149: 1980
A150: TOLEDO - ROYAL PARK FOREST | B150: Diego Gomes | C150: OS TOLEDO ALUGUEL DE EQUIPAMENTOS LTDA | D150: LOCACAO DE MAQUINA PERFURATRIZ DE CONCRETO | E150: 46146 | F150: 1290
A151: TOLEDO - ROYAL PARK FOREST | B151: Diego Gomes | C151: OS TOLEDO ALUGUEL DE EQUIPAMENTOS LTDA | D151: LOCACAO DE MARTELO ROMPEDOR | E151: 46146 | F151: 430
A152: CASCAVEL - ROYAL PLAZA | B152: Eduardo Marques | C152: 51.980.119 JOSE FERNANDO DE CARLI | D152: PORTINHOLA PARA SHAFT | E152: 46146 | F152: 24800
A153: TOLEDO - ROYAL PARK FOREST | B153: Diego Gomes | C153: OS TOLEDO ALUGUEL DE EQUIPAMENTOS LTDA | D153: LOCACAO DE MARTELO ROMPEDOR | E153: 46146 | F153: 1875
A154: TOLEDO - ROYAL PARK FOREST | B154: Diego Gomes | C154: OS TOLEDO ALUGUEL DE EQUIPAMENTOS LTDA | D154: LOCACAO BETONEIRA 400 L | E154: 46146 | F154: 350
A155: TOLEDO - ROYAL PARK FOREST | B155: Diego Gomes | C155: 2E MONTAGEM E MANUTENCAO INDUSTRIAL LTDA | D155: LOCACAO DE CAMINHAO MUNCK | E155: 46146 | F155: 2940
A156: TOLEDO - ROYAL PARK FOREST | B156: Diego Gomes | C156: OS TOLEDO ALUGUEL DE EQUIPAMENTOS LTDA | D156: LOCACAO PECAS PARA ANDAIME | E156: 46146 | F156: 1420
A157: CASCAVEL - DUO VILLE RESIDENCE | B157: Diego Gomes | C157: PRADO E PRADO COMERCIO DE FERRO E ACO LTDA | D157: TRANSPORTES E FRETES | E157: 46146 | F157: 160
A158: TOLEDO - ROYAL PARK FOREST | B158: Diego Gomes | C158: OS TOLEDO ALUGUEL DE EQUIPAMENTOS LTDA | D158: MATERIAIS PARA MANUTENCAO DE MAQUINAS E EQUIPAMENTOS | E158: 46146 | F158: 2380
A159: TOLEDO - ROYAL PARK FOREST | B159: Diego Gomes | C159: MESTRE DA OBRA TOLEDO | D159: LOCACAO DE MAQUINA DE PINTURA (TIPO AIRLESS) | E159: 46146 | F159: 1930
A160: CASCAVEL - ROYAL PLAZA | B160: Eduardo Marques | C160: DISPAVEL DISTRIBUIDORA DE PARAFUSOS CASCAVEL LTDA. | D160: PARABOLT | E160: 46146 | F160: 564
... A224: CASCAVEL - ROYAL PLAZA | B224: Eduardo Marques | C224: L3 CASCAVEL ALUGUEL DE EQUIPAMENTOS LTDA | D224: LOCACAO DE ANDAIME MULTIDIRECIONAL | E224: 46139 | F224: 5000
A225: MARINGA - FORTE DE ATHENA | B225: Lucas Gaspar | C225: CONTAINERS MARINGA LOCACAO E COMERCIO DE EQUIPAMENTOS LTDA | E225: 46139
A226: PARANAVAI - TERRA DE SANTA CRUZ II | B226: Flavia Shigueoka | C226: SUPERMERCADO GUGUY LTDA | D226: CAFE EM PO | E226: 46139 | F226: 283.9025
A227: PARANAVAI - TERRA DE SANTA CRUZ II | B227: Flavia Shigueoka | C227: SUPERMERCADO GUGUY LTDA | D227: PRATO | E227: 46139 | F227: 10.3496
A228: PARANAVAI - TERRA DE SANTA CRUZ II | B228: Flavia Shigueoka | C228: SUPERMERCADO GUGUY LTDA | D228: FILTRO DESCARTAVEL PARA CAFE Nº 103 | E228: 46139 | F228: 23.6902
A229: PARANAVAI - TERRA DE SANTA CRUZ II | B229: Flavia Shigueoka | C229: SUPERMERCADO GUGUY LTDA | D229: PAPEL HIGIENICO | E229: 46139 | F229: 47.8551
A230: PARANAVAI - TERRA DE SANTA CRUZ II | B230: Flavia Shigueoka | C230: SUPERMERCADO GUGUY LTDA | D230: REFRIGERANTE 2 LITROS | E230: 46139 | F230: 34.1633
A231: CASCAVEL - ROYAL PLAZA | B231: Eduardo Marques | C231: AZRB PRODUTOS E SERVICOS DE REPARO EM SUPERFICIES LTDA | D231: CANETA DE LUZ FOTOPOLIMERIZADORA | E231: 46139 | F231: 285.78
A232: CASCAVEL - ROYAL PLAZA | B232: Eduardo Marques | C232: AZRB PRODUTOS E SERVICOS DE REPARO EM SUPERFICIES LTDA | D232: RESINA | E232: 46139 | F232: 2541
A233: MARINGA - AVALON RESIDENCIAL | B233: Lucas Gaspar | C233: WESLEY FERREIRA SILVA 07826489911 | D233: LOCACAO DE EMPILHADEIRA | E233: 46139 | F233: 1267
A234: MARINGA - AVALON RESIDENCIAL | B234: Lucas Gaspar | C234: VANESSA BARBOSA PROFETA 11064211917 | D234: SERVICO DE MANUTENCAO DE MAQUINAS E EQUIPAMENTOS | E234: 46139 | F234: 310
A235: ARAPONGAS - ROYAL PARADISE | B235: Gustavo Sana | C235: TEIXEIRA MARQUES COMERCIAL LTDA | D235: CAP FERRO GALVANIZADO 2.1/2" | E235: 46139 | F235: 122.8
A236: ARAPONGAS - ROYAL PARADISE | B236: Gustavo Sana | C236: TEIXEIRA MARQUES COMERCIAL LTDA | D236: UNIAO PARA PEX 20MM - AGUA FRIA | E236: 46139 | F236: 496.06
A237: MARINGA - AVALON RESIDENCIAL | B237: Lucas Gaspar | C237: ELETRONORTE MARINGA COM. FERRAMENTAS E SERVIÇOS | D237: SERVICO DE MANUTENCAO DE MAQUINAS E EQUIPAMENTOS | E237: 46139 | F237: 889
A238: CASCAVEL - ROYAL PLAZA | B238: Eduardo Marques | C238: V. R. DE SOUZA FERRAGENS LTDA. | D238: JOELHO 45º PVC SOLDAVEL 32MM 22140329 | E238: 46139 | F238: 40
A239: MARINGA - TERRA DE SANTA CRUZ II | C239: ENTEC DISK ENTULHOS LTDA | D239: SERVICO DE LOCACAO DE CACAMBA 5M3 DE RESIDUOS | E239: 46139 | F239: 820
A240: MARINGA - FORTE DE ATHENA | B240: Lucas Gaspar | C240: CONSELHO REGIONAL DE ENGENHARIA E AGRONOMIA DO PARANA | D240: ANOTACAO DE RESPONSABILIDADE TECNICA - ART | E240: 46139 | F240: 108.39
A241: CASCAVEL - ROYAL PLAZA | B241: Eduardo Marques | C241: AZRB PRODUTOS E SERVICOS DE REPARO EM SUPERFICIES LTDA | D241: LIXA MASSA MANUAL Nº220 | E241: 46139 | F241: 187
A242: MARINGA - FORTE DE ATHENA | B242: Lucas Gaspar | C242: ELETRONORTE MARINGA COM. FERRAMENTAS E SERVIÇOS | D242: SERVICO DE MANUTENCAO DE MAQUINAS E EQUIPAMENTOS | E242: 46139 | F242: 927
A243: CASCAVEL - ROYAL PLAZA | B243: Eduardo Marques | C243: 57.673.209 JESSICA TAVARES CHAGAS | D243: BARRACAO | E243: 46139 | F243: 1320
A244: ASSIS - FORTE VILLAGE | B244: Gustavo Sana | C244: HOTEL HIPERION LTDA | D244: DESPESAS COM HOSPEDAGEM | E244: 46136 | F244: 110
A245: ASSIS - FORTE VILLAGE | B245: Gustavo Sana | C245: PEREIRA SERRALHERIA E COMERCIO DE FERRAGENS LTDA | D245: MATERIAIS DIVERSOS PARA SERRALHERIA | E245: 46136 | F245: 3980
A246: ASSIS - FORTE VILLAGE | B246: Gustavo Sana | C246: ASSIS LOCACOES E COMERCIO DE FERRAMENTAS LTDA | D246: LOCACAO PECAS PARA ANDAIME | E246: 46136 | F246: 4142
A247: ARAPONGAS - ROYAL PARADISE | B247: Gustavo Sana | C247: HOTEL HIPERION LTDA | D247: DESPESAS COM HOSPEDAGEM | E247: 46136 | F247: 110
A248: CASCAVEL - ROYAL PLAZA | B248: Eduardo Marques | C248: MATERIAIS DE CONTRUCAO LIDER LTDA | D248: MATERIAL PARA EXECUCAO SERVIÇO DE DRYWALL | E248: 46136 | F248: 19812.5
A249: CASCAVEL - ROYAL PLAZA | B249: Eduardo Marques | C249: HOTEL HIPERION LTDA | D249: DESPESAS COM HOSPEDAGEM | E249: 46135 | F249: 110
A250: CASCAVEL - ROYAL PLAZA | B250: Eduardo Marques | C250: COMERCIAL ELETRICA DZ LTDA | D250: DISJUNTOR DR 80A 30MA | E250: 46135 | F250: 135.9971
A251: CASCAVEL - ROYAL PLAZA | B251: Eduardo Marques | C251: V. R. DE SOUZA FERRAGENS LTDA. | D251: TERMINAL TUBULAR ILHOS 25MM | E251: 46135 | F251: 10.5
... A280: CASCAVEL - DUO VILLE RESIDENCE | B280: Diego Gomes | C280: OMORI E SUZAKI CASCAVEL ALUGUEL DE EQUIPAMENTOS LTDA. | D280: LOCACAO DE MARTELO ROMPEDOR | E280: 46135 | F280: 1300
A281: ASSIS - FORTE VILLAGE | B281: Gustavo Sana | C281: HOTEL HIPERION LTDA | E281: 46135
A282: CASCAVEL - ROYAL PLAZA | B282: Eduardo Marques | C282: V. R. DE SOUZA FERRAGENS LTDA. | D282: PLUGUE MACHO 2P+T 20A | E282: 46135 | F282: 68
A283: CASCAVEL - ROYAL PLAZA | B283: Eduardo Marques | C283: AGFABI COMERCIO DE TINTAS LTDA | D283: LONA PRETA 4X100M 150 MICRAS | E283: 46135 | F283: 133
A284: ARAPONGAS - ROYAL PARADISE | B284: Gustavo Sana | C284: ELETROLONDRIFIOS COM. DE MATERIAL ELETRICO LTDA | D284: CABO QUADRUPLEX | E284: 46135 | F284: 1960
A285: CASCAVEL - ROYAL PLAZA | B285: Eduardo Marques | C285: JAF MATERIAS DE CONSTRUCAO LTDA. | D285: PEDRISCO | E285: 46135 | F285: 1199.1
A286: CASCAVEL - ROYAL PLAZA | B286: Eduardo Marques | C286: AGFABI COMERCIO DE TINTAS LTDA | D286: THINNER FORTE | E286: 46135 | F286: 279
A287: ASSIS - FORTE VILLAGE | B287: Gustavo Sana | C287: MARTINS & PIEMONTE ASSIS ALUGUEL DE EQUIPAMENTOS E COMERCIO DE MAQUINAS LTDA | D287: LOCACAO PECAS PARA ANDAIME | E287: 46135 | F287: 1060
A288: CASCAVEL - ROYAL PLAZA | B288: Eduardo Marques | C288: COMERCIAL ELETRICA DZ LTDA | D288: DISJUNTOR BIPOLAR PADRAO IEC TIPO C DE 63A | E288: 46135 | F288: 75.5715
A289: CASCAVEL - ROYAL PLAZA | B289: Eduardo Marques | C289: COMERCIAL ELETRICA DZ LTDA | D289: BARRAMENTO NEUTRO / TERRA | E289: 46135 | F289: 8.3579
A290: CASCAVEL - ROYAL PLAZA | B290: Eduardo Marques | C290: COMERCIAL ELETRICA DZ LTDA | D290: DISJUNTOR TRIPOLAR PADRAO IEC TIPO C 32A | E290: 46135 | F290: 46.522
A291: CASCAVEL - ROYAL PLAZA | B291: Eduardo Marques | C291: COMERCIAL ELETRICA DZ LTDA | D291: DISJUNTOR BIPOLAR PADRAO IEC TIPO C DE 32A | E291: 46135 | F291: 33.4882
A292: CASCAVEL - ROYAL PLAZA | B292: Eduardo Marques | C292: COMERCIAL ELETRICA DZ LTDA | D292: BARRAMENTO NEUTRO / TERRA | E292: 46135 | F292: 16.7272
A293: CASCAVEL - ROYAL PLAZA | B293: Eduardo Marques | C293: COMERCIAL ELETRICA DZ LTDA | D293: DISJUNTOR BIPOLAR PADRAO IEC TIPO C 16A | E293: 46135 | F293: 32.3361
A294: CASCAVEL - ROYAL PLAZA | B294: Eduardo Marques | C294: AGFABI COMERCIO DE TINTAS LTDA | D294: FITA CREPE 48MMX50M | E294: 46135 | F294: 297
A295: PAIÇANDU - TERRA DE SANTA CRUZ | B295: Flavia Shigueoka | C295: ALFA MÁQUINAS COMÉRCIO E SERVIÇOS LTDA | E295: 46135
A296: FOZ DO IGUAÇU - ROYAL LEGACY | B296: Diego Gomes | C296: FERCAM MATERIAIS DE CONSTRUCAO LTDA | E296: 46135
A297: CASCAVEL - DUO VILLE RESIDENCE | B297: Diego Gomes | C297: ESTACILIO JOSE CARDOSO e CIA LTDA | D297: TOMADA INDUSTRIAL FEMEA 3P+T 32A | E297: 46135 | F297: 22.13
A298: CASCAVEL - DUO VILLE RESIDENCE | B298: Diego Gomes | C298: ESTACILIO JOSE CARDOSO e CIA LTDA | D298: QUADRO DE COMANDO SOBREPOR CE 500X500X200MM | E298: 46135 | F298: 967.28
A299: CASCAVEL - DUO VILLE RESIDENCE | B299: Diego Gomes | C299: ESTACILIO JOSE CARDOSO e CIA LTDA | D299: TRILHO PARA DISJUNTOR EM ALUMINIO PERFURADO PARA DISJUNTOR DIM 25CM | E299: 46135 | F299: 16.64
...

Sheet Resumo_Obras
A1: Obra | B1: Valor Total
A2: PORTO RICO - NEO WAVE | B2: =SUMIF([1]Especificação!A:A,A2,[1]Especificação!F:F) -> 47259.718
A3: MARINGA - FORTE DE ATHENA | B3: =SUMIF([1]Especificação!A:A,A3,[1]Especificação!F:F) -> 40226.102
A4: CASCAVEL - DUO VILLE RESIDENCE | B4: =SUMIF([1]Especificação!A:A,A4,[1]Especificação!F:F) -> 202876.53
A5: PAIÇANDU - TERRA DE SANTA CRUZ | B5: =SUMIF([1]Especificação!A:A,A5,[1]Especificação!F:F) -> 29925.973
A6: PARANAVAI - TERRA DE SANTA CRUZ II | B6: =SUMIF([1]Especificação!A:A,A6,[1]Especificação!F:F) -> 226777.76
A7: CASCAVEL - ROYAL PLAZA | B7: =SUMIF([1]Especificação!A:A,A7,[1]Especificação!F:F) -> 328793.19
A8: ARAPONGAS - ROYAL PARADISE | B8: =SUMIF([1]Especificação!A:A,A8,[1]Especificação!F:F) -> 212835.58
A9: MARINGA - FORTE DE ARUNDEL | B9: =SUMIF([1]Especificação!A:A,A9,[1]Especificação!F:F) -> 413033.6
A10: MARINGA - AVALON RESIDENCIAL | B10: =SUMIF([1]Especificação!A:A,A10,[1]Especificação!F:F) -> 38212.74
A11: TOLEDO - ROYAL PARK FOREST | B11: =SUMIF([1]Especificação!A:A,A11,[1]Especificação!F:F) -> 348820.94
A12: MARINGA - TERRA DE SANTA CRUZ II | B12: =SUMIF([1]Especificação!A:A,A12,[1]Especificação!F:F) -> 14779.89
A13: UMUARAMA - ROYAL PORTO DOURADO | B13: =SUMIF([1]Especificação!A:A,A13,[1]Especificação!F:F) -> 48295.87
... A17: MARINGA - ROYAL PALACE | B17: =SUMIF([1]Especificação!A:A,A17,[1]Especificação!F:F) -> 304.2

Sheet Resumo_Coordenadores
A1: Coordenador | B1: Valor Total
A2: Diego Gomes | B2: =SUMIF([1]Especificação!B:B,A2,[1]Especificação!F:F) -> 599993.34
A3: Eduardo Marques | B3: =SUMIF([1]Especificação!B:B,A3,[1]Especificação!F:F) -> 328793.19
A4: Flavia Shigueoka | B4: =SUMIF([1]Especificação!B:B,A4,[1]Especificação!F:F) -> 303963.45
A5: Gustavo Sana | B5: =SUMIF([1]Especificação!B:B,A5,[1]Especificação!F:F) -> 421163.7
A6: Lucas Gaspar | B6: =SUMIF([1]Especificação!B:B,A6,[1]Especificação!F:F) -> 491472.44

Sheet Todos_Insumos
A1: Insumo | B1: Valor Total
A2: MATERIAL PARA EXECUCAO SERVIÇO DE DRYWALL | B2: 315996.65
A3: MATERIAIS DIVERSOS - FATURAMENTO DIRETO | B3: 285212.5
A4: PAVER | B4: 168255
A5: DECORACAO - AMBIENTE PLAYGROUND | B5: 66000
A6: BRITA | B6: 65955.3
A7: MATERIAIS DIVERSOS PARA SERRALHERIA | B7: 52725.84
A8: LOCACAO DE CAMINHAO MUNCK | B8: 43194.004
A9: SERVICO DE EXECUCAO TODAS AS PAREDES EM DRYWALL ST E RU APTOS | B9: 38526.707
A10: BRITA GRADUADA | B10: 36421.398
A11: SERVICOS DE MAO DE OBRA SERRALHERIA | B11: 34780
A12: LOCACAO DE MINI CARREGADEIRA | B12: 29500.608
A13: ACESSORIOS PARA FORMA E SISTEMA DE SEGURANCA | B13: 29498.5
... A543: GUARDANAPO DE PAPEL | B543: 3.9405

Sheet Todos_Fornecedores
A1: Fornecedor | B1: Valor Total
A2: ELG SOLUCOES CONSTRUTIVAS - EIRELI | B2: 251152.8
A3: IVAÍ ARTEFATOS DE CIMENTO LTDA | B3: 160855
A4: M F - EQUIPAMENTOS DE PROTECAO INDIVIDUAL E COLETIVO LTDA | B4: 95099.94
A5: 50.421.151 ANGELA HONORIA DO PRADO | B5: 91448.5
A6: LUCIANO NEVES CRACCO | B6: 88728
A7: M LACHI LOPES COMERCIO DE GESSO LTDA | B7: 80003.344
A8: ART METAL METALURGICA LTDA | B8: 66725
A9: W KATSUMI OGAWA & CIA LTDA | B9: 66000
A10: MATERIAIS DE CONTRUCAO LIDER LTDA | B10: 64146.25
A11: BIGOLIN MATERIAIS DE CONSTRUCAO LTDA | B11: 54615.656
A12: CIB MINERACAO LTDA | B12: 39129
A13: MILENIUM METALURGICA LTDA | B13: 34849
... A208: FERCAM MATERIAIS DE CONSTRUCAO LTDA | B208: 0
